portals/__init__.py
portals/version.py
spacetime_portals-0.0.1a0.dist-info/LICENSE.txt
spacetime_portals-0.0.1a0.dist-info/METADATA
spacetime_portals-0.0.1a0.dist-info/WHEEL
spacetime_portals-0.0.1a0.dist-info/top_level.txt
spacetime_portals-0.0.1a0.dist-info/RECORD
