Metadata-Version: 2.1
Name: spacetime-portals
Version: 0.0.1a0
Summary: UNKNOWN
Home-page: UNKNOWN
Author: sahn
Author-email: jam31118@gmail.com
License: GPLv3
Keywords: physics,quantum mechanics,simulation
Platform: UNKNOWN
Classifier: Topic :: Scientific/Engineering :: Physics
Classifier: License :: OSI Approved :: GNU Affero General Public License v3
Classifier: Programming Language :: Python :: 3.8
Requires-Dist: numpy
